[
"month_sum_calc_values":173
"calculations_model_station"
{
"stationid":
"modelid":
"calculationid":

},

"calc_structure": "persons_calculations_model_station"
{
"stationid":
"modelid":
"calculationid":
"person":

},

"daynum_person_calculations_model_station"
{
"stationid":
"modelid":
"calculationid":
"person":
"daynum":
},

"values_daynum_person_calculations_model_station"
{
"stationid":
"modelid":
"calculationid":
"person":
"daynum":
"dayvalue":
},



"Station_calc_person_day_values"{
"stationid":
"modelid":
"calculationid":
"person":
"daynum":
"dayvalue":
},
""
{
"stationid":
"modelid":
"calculationid":
"person":
"daynum":
"dayvalue":
},
""
{
"stationid":
"modelid":
"calculationid":
"daynum":
"dayvalue":
}
]